{
  "lastAlerts": {},
  "lastUpdates": {
    "277730007_de:12069:900220476::1": {
      "timestamp": 1763227365738,
      "delay": 11037,
      "routeId": "18915_700"
    },
    "278898473_900210003": {
      "timestamp": 1763249810317,
      "delay": 7860,
      "routeId": "24025_100"
    },
    "278898473_900210007": {
      "timestamp": 1763249810317,
      "delay": 7800,
      "routeId": "24025_100"
    },
    "278898473_900029305": {
      "timestamp": 1763249810317,
      "delay": 7800,
      "routeId": "24025_100"
    },
    "278898473_900029101": {
      "timestamp": 1763249810317,
      "delay": 7800,
      "routeId": "24025_100"
    },
    "278898473_900020201": {
      "timestamp": 1763249810317,
      "delay": 7740,
      "routeId": "24025_100"
    },
    "278898473_900003200": {
      "timestamp": 1763249810317,
      "delay": 7800,
      "routeId": "24025_100"
    }
  },
  "lastRun": "2025-11-16T04:14:44.677Z"
}